Workbook

Sheet ingresos
A1: TIPO | B1: CUFE/CUDE | C1: Folio | D1: Fecha Emisión | E1: NIT Emisor | F1: Nombre Emisor | G1: NIT Receptor | H1: Nombre Receptor | I1: SUBTOTAL | J1: IVA | K1: IC | L1: INC | M1: INC Bolsas | N1: Total
A2: Factura electrónica | B2: 0ca529a4eb298c18d480562f77e345f92b464cc18b8ccb83f0f630dabf30fc547ea3e4dd1d319d701ed16d92edad320e | C2: 1 | D2: 45722 | E2: 901907732 | F2: TECNOTICS SAS | G2: 811026805 | H2: PANACAMBIOS Y CIA LTDA | I2: =+N2-M2-L2-K2-J2 -> 550000 | J2: 104500 | K2: 0 | L2: 0 | M2: 0 | N2: 654500
A3: Factura electrónica | B3: bc7e4abaa565e3360dac35f42cccceb4bbbd3626328f38a5fd9e96a60a778981109b3b795d3b4ee0c5f505fe407e1cad | C3: 2 | D3: 45722 | E3: 901907732 | F3: TECNOTICS SAS | G3: 900208742 | H3: MAGNISEGUROS ASESORES EN SEGUROS LIMITADA | I3: =+N3-M3-L3-K3-J3 -> 200000 | J3: 0 | K3: 0 | L3: 0 | M3: 0 | N3: 200000
A4: Factura electrónica | B4: 287efd1111d9df3f1d35981d477437a3935829354fb79c214338a3cdfe104f0ebce51f0c4464a104b47ec9a2a5a848a9 | C4: 3 | D4: 45722 | E4: 901907732 | F4: TECNOTICS SAS | G4: 811044610 | H4: INGENIERIA HOSPITALARIA S.A.S | I4: =+N4-M4-L4-K4-J4 -> 650000 | J4: 123500 | K4: 0 | L4: 0 | M4: 0 | N4: 773500
A5: Factura electrónica | B5: d717c9894107f58afe544d83f3b04368108a1719b77d6e11c76005b9cbfbf90b39bca792850ceda3f2897f81696a223d | C5: 4 | D5: 45722 | E5: 901907732 | F5: TECNOTICS SAS | G5: 901495799 | H5: LUSEO COLOMBIA S.A.S | I5: =+N5-M5-L5-K5-J5 -> 1650000 | J5: 313500 | K5: 0 | L5: 0 | M5: 0 | N5: 1963500
A6: Factura electrónica | B6: 75231292c4b4a470e70655ca3e1b3b261d3a83e02be31336c3397365382a6404fb39a5ff3a5f293f457d1fb581f8f5bf | C6: 5 | D6: 45722 | E6: 901907732 | F6: TECNOTICS SAS | G6: 901495799 | H6: LUSEO COLOMBIA S.A.S | I6: =+N6-M6-L6-K6-J6 -> 1584738 | J6: 0 | K6: 0 | L6: 0 | M6: 0 | N6: 1584738
A7: Factura electrónica | B7: da965cc736422b2136d3bc9ee0868612c58cb1790bf29dbc23c90357a3088520b3d7db46e09fb537a4cd81b332f5c610 | C7: 6 | D7: 45722 | E7: 901907732 | F7: TECNOTICS SAS | G7: 830087371 | H7: TRANSPORTE ESPECIAL RUTA 07 S.A.S. | I7: =+N7-M7-L7-K7-J7 -> 1072018 | J7: 0 | K7: 0 | L7: 0 | M7: 0 | N7: 1072018
A8: Factura electrónica | B8: bb192f48ce7d0039100ee6d7941917e9c4d5a9bb2640566606ac037d2b5d064eada81e0e21e5ff54b00bc6f3bb4a4dbe | C8: 7 | D8: 45722 | E8: 901907732 | F8: TECNOTICS SAS | G8: 901774691 | H8: TIERRAFRIA ARQUITECTURA S.A.S | I8: =+N8-M8-L8-K8-J8 -> 367811 | J8: 0 | K8: 0 | L8: 0 | M8: 0 | N8: 367811
A9: Factura electrónica | B9: 1563a4b96c509c44e757f16d7ee724f24ad8e5a5054346260748fa259516f8cc2debf79afbcd04ea11127f5422cfe4a9 | C9: 8 | D9: 45722 | E9: 901907732 | F9: TECNOTICS SAS | G9: 900383497 | H9: INATHA S.A.S. | I9: =+N9-M9-L9-K9-J9 -> 430000 | J9: 81700 | K9: 0 | L9: 0 | M9: 0 | N9: 511700
A10: Factura electrónica | B10: 9a7a3c925620ebe9f7162021877c41ae22b92e44baf63770911041fb15e958d6569a624b68c2ce392dec9609012d7b4d | C10: 9 | D10: 45723 | E10: 901907732 | F10: TECNOTICS SAS | G10: 901884325 | H10: MEDELL?N DEVELOPMENT ECOSYSTEM S.A.S. | I10: =+N10-M10-L10-K10-J10 -> 367811 | J10: 0 | K10: 0 | L10: 0 | M10: 0 | N10: 367811
A11: Factura electrónica | B11: fa06717c752227527f2b35de5c770807ca37e91e0594607d2592904c5e532b7d9e0a86d28b261f4f5fa9915995384643 | C11: 10 | D11: 45910 | E11: 901907732 | F11: TECNOTICS SAS | G11: 117142370 | H11: Daniel Alejandro Martinez Velez | I11: =+N11-M11-L11-K11-J11 -> 100 | J11: 0 | K11: 0 | L11: 0 | M11: 0 | N11: 100
A12: Factura electrónica | B12: 187a7140782c15e4c06605f2b0a0043142850b893f8563f5e8cc9d149070522da5c0e579ec09f757bed4995a5094fbcc | C12: 10 | D12: 45723 | E12: 901907732 | F12: TECNOTICS SAS | G12: 900383497 | H12: INATHA S.A.S. | I12: =+N12-M12-L12-K12-J12 -> 430000 | J12: 0 | K12: 0 | L12: 0 | M12: 0 | N12: 430000
A13: Factura electrónica | B13: bf90fd36af5a60d3650d9a56d2ac9641fb543f230d2c09e3587f15faec491d844e96d1f419e2256abf3e4f2fe9e933f6 | C13: 12 | D13: 45910 | E13: 901907732 | F13: TECNOTICS SAS | G13: 117142370 | H13: Daniel Alejandro Martinez Velez | I13: =+N13-M13-L13-K13-J13 -> 100 | J13: 0 | K13: 0 | L13: 0 | M13: 0 | N13: 100
... A323: Factura electrónica | B323: 2c08dbc901779beeb0abac73c0a4e2072e210913f2b5c518de54c76ed9ea90e3d1dd1d06e61d04a853b3b60ef343b9f4 | C323: 317 | D323: 46021 | E323: 901907732 | F323: TECNOTICS SAS | G323: 811017918 | H323: FUMIAGRO S.A.S. | I323: =+N323-M323-L323-K323-J323 -> 6460000 | J323: 0 | K323: 0 | L323: 0 | M323: 0 | N323: 6460000
A324: Nota de crédito electrónica | B324: 6337f55a1f7bee8e17b6fd6a52d49da9ef1f875222dfd6037c781e9acc6ada0cb072de4681eb32c2a264df36a420ca54 | C324: NC21 | D324: 45723 | E324: 901907732 | F324: TECNOTICS SAS | G324: 901774691 | H324: TIERRAFRIA ARQUITECTURA S.A.S | I324: =+N324-M324-L324-K324-J324 -> -367811 | J324: 0 | K324: 0 | L324: 0 | M324: 0 | N324: -367811
A325: Nota de crédito electrónica | B325: 0962a335e07554d51ee7bdfac2a691ea5713985e9e1c9d83bc474cf3249c6ce191b099265a416358787b0c528501df97 | C325: NC210 | D325: 45870 | E325: 901907732 | F325: TECNOTICS SAS | G325: 900643097 | H325: HEMOGROUP S.A.S | I325: =+N325-M325-L325-K325-J325 -> -3110206 | J325: -218500 | K325: 0 | L325: 0 | M325: 0 | N325: -3328706
A326: Nota de crédito electrónica | B326: 4805a21884b61c4fda831bd82c76debecb1530f6b098bcab3b3d5260a8cb8f85a29d1b212644b171a640401b8dff2fa0 | C326: NC211 | D326: 45898 | E326: 901907732 | F326: TECNOTICS SAS | G326: 811044610 | H326: INGENIERIA HOSPITALARIA S.A.S | I326: =+N326-M326-L326-K326-J326 -> -8150000 | J326: -43700 | K326: 0 | L326: 0 | M326: 0 | N326: -8193700
A327: Nota de crédito electrónica | B327: 57e129a39630a44ae62e80b65aa7e982213cea72279af70ed534997ebedc618d33d7a7d2697cfec1edd19bc53797d98a | C327: NC212 | D327: 45940 | E327: 901907732 | F327: TECNOTICS SAS | G327: 830087371 | H327: TRANSPORTE ESPECIAL RUTA 07 S.A.S. | I327: =+N327-M327-L327-K327-J327 -> -16875000 | J327: 0 | K327: 0 | L327: 0 | M327: 0 | N327: -16875000
A328: Nota de crédito electrónica | B328: 9793693d019c9ab9cd1a27c53aab9e03fb42c6bb80606edb80108c87b41f1003e6526318c986ead641ec025d371157bf | C328: NC213 | D328: 45947 | E328: 901907732 | F328: TECNOTICS SAS | G328: 811000784 | H328: TERMINAL DEL SUR DE MEDELLIN PH | I328: =+N328-M328-L328-K328-J328 -> -456000 | J328: -86640 | K328: 0 | L328: 0 | M328: 0 | N328: -542640
A329: Nota de crédito electrónica | B329: 6a61e930a99d229bd24221bcccc26aa60aaa6b11fae51798eab72cab1f1bdd60e407afa8b8eff92f44208563d429c6e1 | C329: NC214 | D329: 45955 | E329: 901907732 | F329: TECNOTICS SAS | G329: 901344156 | H329: TRANS CONCORD TRAVEL S.A.S | I329: =+N329-M329-L329-K329-J329 -> -1550000 | J329: -57000 | K329: 0 | L329: 0 | M329: 0 | N329: -1607000
A330: Nota de crédito electrónica | B330: 0c4b839113e765fb7442cc03cd44630c5a0530e33769ef14f0e49190e659f9e28e5ee911e8606d51c6df0c9e26b0dee1 | C330: NC215 | D330: 45955 | E330: 901907732 | F330: TECNOTICS SAS | G330: 890910970 | H330: TRANSPORTES JERICO, PUEBLORICO, TARSO S.A.S. | I330: =+N330-M330-L330-K330-J330 -> -1550000 | J330: 0 | K330: 0 | L330: 0 | M330: 0 | N330: -1550000
A331: Nota de crédito electrónica | B331: 41163a4559d4a60e00d26ac513fc6677f289985fa77066283f2dadebeb10f761a22eeb52109512547243e4d19ea05a3c | C331: NC216 | D331: 45963 | E331: 901907732 | F331: TECNOTICS SAS | G331: 901225179 | H331: INNOVACIÓN ESTRATÉGICA - INNOVATE S.A.S. | I331: =+N331-M331-L331-K331-J331 -> -868854 | J331: 0 | K331: 0 | L331: 0 | M331: 0 | N331: -868854
A332: Nota de crédito electrónica | B332: e76db0627546ce847a644d55c9cdb1dc026a6910a97ba9c741ccb63128a906991a853bb874ed350c2982b9295874ed8c | C332: NC217 | D332: 45973 | E332: 901907732 | F332: TECNOTICS SAS | G332: 900688446 | H332: CONSTRUREDES GRUPO GOMEZ | I332: =+N332-M332-L332-K332-J332 -> -1020000 | J332: -193800 | K332: 0 | L332: 0 | M332: 0 | N332: -1213800
A333: Nota de crédito electrónica | B333: 7a8ffb4f608d05c82cae350daf681dd91a0c4ba0391349c142ee01efc2e7c24cfa65a024acfa6fb48fae3450fa7920b8 | C333: NC218 | D333: 45975 | E333: 901907732 | F333: TECNOTICS SAS | G333: 900688446 | H333: CONSTRUREDES GRUPO GOMEZ | I333: =+N333-M333-L333-K333-J333 -> -1244546.2 | J333: -236463.78 | K333: 0 | L333: 0 | M333: 0 | N333: -1481010
A334: Nota de crédito electrónica | B334: 6a7423df234b0703d5e63b72a4dd47fe99b6bb07c3cbfe6322ac267ccfb9add3591c8a7ec804a123d3f0b07a37ff5263 | C334: NC219 | D334: 45990 | E334: 901907732 | F334: TECNOTICS SAS | G334: 900742678 | H334: LIFEHEALTH UNIVERSAL EXPORT SAS | I334: =+N334-M334-L334-K334-J334 -> -650000 | J334: -123500 | K334: 0 | L334: 0 | M334: 0 | N334: -773500
A335: Nota de crédito electrónica | B335: 0aab57ed6fd68ee08c575bae8d787268f60738dc0db999b3ecf18ede1ef7d6635b168bd0753ae8431fae98935077e58a | C335: NC22 | D335: 45723 | E335: 901907732 | F335: TECNOTICS SAS | G335: 900383497 | H335: INATHA S.A.S. | I335: =+N335-M335-L335-K335-J335 -> -430000 | J335: -81700 | K335: 0 | L335: 0 | M335: 0 | N335: -511700
... A342: Nota de crédito electrónica | B342: 6eee1740a9991f4923e40505e83ee7ebe63eb9df702703a0f13f36ddcfadd88a8e136848120248e8ff0234200aefd666 | C342: NC29 | D342: 45856 | E342: 901907732 | F342: TECNOTICS SAS | G342: 900825963 | H342: IDINNOV S.A.S. | I342: =+N342-M342-L342-K342-J342 -> -338919 | J342: -23750 | K342: 0 | L342: 0 | M342: 0 | N342: -362669
I343: =SUM(I2:I342) -> 5.1584656e+08 | J343: =SUM(J2:J342) -> 44511560 | K343: =SUM(K2:K342) -> 0 | L343: =SUM(L2:L342) -> 0 | M343: =SUM(M2:M342) -> 0 | N343: =SUM(N2:N342) -> 5.6035812e+08

Sheet Hoja3ok
A1: Suma de SUBTOTAL | C1: TIPO
A2: NIT Receptor | B2: Nombre Receptor | C2: Factura electrónica | D2: Nota de crédito electrónica | E2: Total general
A3: 21993269 | B3: I.E El Rosario de Bello | C3: 12862964 | E3: 12862964 | F3: sin retencion
A4: 98532400 | B4: Juan David Sánchez López | C4: 2483000 | E4: 2483000 | F4: sin retencion
A5: 117142370 | B5: Daniel Alejandro Martinez Velez | C5: 500 | E5: 500 | F5: sin retencion
A6: 811000784 | B6: TERMINAL DEL SUR DE MEDELLIN PH | C6: 62247339 | D6: -456000 | E6: 61791339
A7: 811017918 | B7: FUMIAGRO S.A.S. | C7: 20771712 | E7: 20771712
A8: 811026805 | B8: PANACAMBIOS Y CIA LTDA | C8: 5500000 | E8: 5500000
A9: 811035110 | B9: CI Global Exchange SAS | C9: 545000 | E9: 545000
A10: 811044610 | B10: INGENIERIA HOSPITALARIA S.A.S | C10: 26846920 | D10: -8150000 | E10: 18696920
A11: 830087371 | B11: TRANSPORTE ESPECIAL RUTA 07 S.A.S. | C11: 41933068 | D11: -16875000 | E11: 25058068
A12: 860022343 | B12: CONGREGACION SANTO DOMINGO | C12: 62700751 | E12: 62700751
A13: 890910970 | B13: TRANSPORTES JERICO, PUEBLORICO, TARSO S.A.S. | C13: 21211744 | D13: -1550000 | E13: 19661744
A14: 890911898 | B14: Stop SAS | C14: 2445000 | E14: 2445000
A15: 890931488 | B15: CENTRO COMERCIAL VILLANUEVA P.H. | C15: 900000 | E15: 900000
A16: 890932241 | B16: TECNIQUIMICASA | C16: 160000 | E16: 160000
A17: 890935751 | B17: LENTES DE CONTACTO S.A.S. | C17: 620000 | E17: 620000
A18: 900177076 | B18: vista norte sas | C18: 1405000 | E18: 1405000
A19: 900208742 | B19: MAGNISEGUROS ASESORES EN SEGUROS LIMITADA | C19: 4140000 | D19: -780000 | E19: 3360000
A20: 900383497 | B20: INATHA S.A.S. | C20: 4752389 | D20: -430000 | E20: 4322389
A21: 900643097 | B21: HEMOGROUP S.A.S | C21: 41395178 | D21: -3110206 | E21: 38284972
A22: 900688446 | B22: CONSTRUREDES GRUPO GOMEZ | C22: 25009856 | D22: -2264546.2 | E22: 22745310
A23: 900727888 | B23: ARRENDAMIENTOS PANORAMA LOS COLORES SAS | C23: 1468240 | E23: 1468240
A24: 900742678 | B24: LIFEHEALTH UNIVERSAL EXPORT SAS | C24: 650000 | D24: -650000 | E24: 0
A25: 900779955 | B25: COMERCIALIZADORA INTERNACIONAL EXUN S.A.S | C25: 3099000 | E25: 3099000
A26: 900825963 | B26: IDINNOV S.A.S. | C26: 1576158 | D26: -927838 | E26: 648320
A27: 900842157 | B27: GRUPO ODONTOLÓGICO SMILE S.A.S | C27: 2408828 | E27: 2408828
A28: 900983772 | B28: VIBART DENTAL CLINIC | C28: 2917782 | E28: 2917782
A29: 901094323 | B29: GIGA ELECTROINGENIERIA SAS | C29: 1800000 | E29: 1800000
A30: 901105552 | B30: 24 H SERVICES S.A.S | C30: 81107275 | E30: 81107275
A31: 901174894 | B31: GILESA SAS | C31: 1867624 | E31: 1867624
A32: 901193232 | B32: SIMA TECH SAS | C32: 1918070 | E32: 1918070
A33: 901196517 | B33: Mas 3 Inmobiliaria SAS | C33: 840000 | E33: 840000
A34: 901225179 | B34: INNOVACIÓN ESTRATÉGICA - INNOVATE S.A.S. | C34: 6950832 | D34: -868854 | E34: 6081978
A35: 901344156 | B35: TRANS CONCORD TRAVEL S.A.S | C35: 17007000 | D35: -1550000 | E35: 15457000
A36: 901428649 | B36: ELECTROMANTENIMIENTO A.C S.A.S | C36: 9156404 | E36: 9156404
A37: 901446911 | B37: DALIAS GROUP S.A.S. | C37: 1161630 | E37: 1161630
A38: 901495799 | B38: LUSEO COLOMBIA S.A.S | C38: 71537872 | D38: -2128439 | E38: 69409433
A39: 901586731 | B39: SOPORTES TECHNOLOGY SAS | C39: 2690000 | E39: 2690000
A40: 901774691 | B40: TIERRAFRIA ARQUITECTURA S.A.S | C40: 4055025 | D40: -1860339 | E40: 2194686
A41: 901799676 | B41: Sales Rain Sas | C41: 1804000 | E41: 1804000
A42: 901805601 | B42: NUESTRA HOUSE SAS | C42: 1880000 | E42: 1880000
A43: 901884325 | B43: MEDELL?N DEVELOPMENT ECOSYSTEM S.A.S. | C43: 2056683 | D43: -476575 | E43: 1580108
A44: 901897598 | B44: MACROLAB ZONA FRANCA S.A.S. | C44: 1360000 | E44: 1360000
A45: 901931446 | B45: Compropósito SAS | C45: 681512.61 | E45: 681512.61
A46: Total general | C46: 5.5792436e+08 | D46: -42077797 | E46: 5.1584656e+08 | F46: ok

Sheet Costos
A1: TIPO | B1: CUFE/CUDE | C1: Folio | D1: Fecha Emisión | E1: NIT Emisor | F1: Nombre Emisor | G1: NIT Receptor | H1: Nombre Receptor | I1: SUBTOTAL | J1: IVA | K1: IC | L1: INC | M1: INC Bolsas | N1: Total
A2: Factura electrónica | B2: e28c09b7699f692230f516beb9b2781f68209a3b04f9b0fc7cba231a8d521792b9fed3c89292e12ed5b4b7b13002d8be | C2: 595069 | D2: 46021 | E2: 800091549 | F2: IMPRESISTEM S A S | G2: 901907732 | H2: TECNOTICS S.A.S. | I2: 289879 | J2: 55077 | K2: 0 | L2: 0 | M2: 0 | N2: 344956
A3: Factura electrónica | B3: ebe95ec7444370efd7a552502fcf29930fcfece6b2b1d8f4d2bdaf209f7425942e2d46552cfa1e06394fe23d108c770b | C3: 954 | D3: 46021 | E3: 901649254 | F3: JSA DISTRIBUCIONES S.A.S. | G3: 901907732 | H3: TECNOTICS S.A.S. | I3: 16114196 | J3: 3061697.2 | K3: 0 | L3: 0 | M3: 0 | N3: 19175893
A4: Factura electrónica | B4: c76dc187c2f78bd833cb701d006628ee54dc3ba62b7136fb89cea1222ed9b2f098fb48ba326cf3b0969a9198987e28c5 | C4: 83 | D4: 46021 | E4: 1003880015 | F4: PAEZ BALLESTEROS CESAR NICOLAS | G4: 901907732 | H4: TECNOTICS SAS | I4: 80000 | J4: 0 | K4: 0 | L4: 0 | M4: 0 | N4: 80000
A5: Factura electrónica | B5: 74b000d75141dc8628c2ba82f6be3da8f1cc9a8bbd76957206b138ac2ad60702b87b4c85cdc7c156f46f2675b65e4561 | C5: 2961 | D5: 46020 | E5: 70561688 | F5: DIEGO ALONSO MURILLO GUZMAN | G5: 901907732 | H5: TECNOTICS SAS | I5: 16000 | J5: 3040 | K5: 0 | L5: 0 | M5: 0 | N5: 19040
A6: Factura electrónica | B6: df22eb1c87b063255405c75c901219dbff066c1a68594d36f17f5bf36a866d7f7d289b55d3f96a12a5318727d0fd30ae | C6: 79837 | D6: 46020 | E6: 900848266 | F6: CONSMO PC MAYORISTA S.A.S | G6: 901907732 | H6: TECNOTICS SAS | I6: 20000 | J6: 3800 | K6: 0 | L6: 0 | M6: 0 | N6: 23800
A7: Factura electrónica | B7: 6c5a072ec87f3488df2a1c0dcbfad8165fa8b384868fe403bab6c3dc7cf99f108e7b4ce5bf1fd8b8fc806f97f19a37f8 | C7: 4256 | D7: 46020 | E7: 3486666 | F7: RAMON ALCIDES CIFUENTES SERNA | G7: 901907732 | H7: TECNOTICS SAS | I7: 20000 | J7: 0 | K7: 0 | L7: 0 | M7: 0 | N7: 20000
A8: Factura electrónica | B8: 9ecf7a065b0598de8815ebdab0a1a977eb6b2e49ef4891d8d866f7490009f8add0399b551298eff88151de53c282fee4 | C8: 729528 | D8: 46015 | E8: 900219834 | F8: F2X S.A.S. | G8: 901907732 | H8: Tecnotics S.A.S | I8: 3781.51 | J8: 718.49 | K8: 0 | L8: 0 | M8: 0 | N8: 4500
A9: Factura electrónica | B9: b10c4fc37a4d66b8c8e3ba04389cb2cc95669bf3fa36c9a6d5b43d0f2776a3a661f4b711f8be659c870db28286e2dae4 | C9: 720444 | D9: 46014 | E9: 900219834 | F9: F2X S.A.S. | G9: 901907732 | H9: Tecnotics S.A.S | I9: 3781.51 | J9: 718.49 | K9: 0 | L9: 0 | M9: 0 | N9: 4500
A10: Documento equivalente - Cobro de peajes | B10: 4cc16ba17f6702d3cdbbbce7fcd53948b186663c63ce33f0f849c999f2adea320a4de4d5a45692a381fad43f8c10982c | C10: 75584379 | D10: 46014 | E10: 900219834 | F10: F2X S.A.S. | G10: 901907732 | H10: Tecnotics S.A.S | I10: 25000 | J10: 0 | K10: 0 | L10: 0 | M10: 0 | N10: 25000
A11: Documento equivalente - Cobro de peajes | B11: 57a1dded2b2cc9efb7d6f48f4d0c9d6967087a8982e1148b1c06f260d81ecab36291300288c903eb43700c0471b12383 | C11: 75544794 | D11: 46014 | E11: 900219834 | F11: F2X S.A.S. | G11: 901907732 | H11: Tecnotics S.A.S | I11: 25000 | J11: 0 | K11: 0 | L11: 0 | M11: 0 | N11: 25000
A12: Factura electrónica | B12: 7fd460ab1ee66ef439559490c092235e92215e22771a1274081de0ee4558dff68aa3b0e51e4038ee2f384b36cbe7d046 | C12: 907 | D12: 46014 | E12: 901649254 | F12: JSA DISTRIBUCIONES S.A.S. | G12: 901907732 | H12: TECNOTICS S.A.S. | I12: 2338676.5 | J12: 444348.53 | K12: 0 | L12: 0 | M12: 0 | N12: 2783025
A13: Factura electrónica | B13: d2d556c9e420610eb62d728be7080a820149b06428682cef711712df243d5848d1ce21af6592f412ed76e716baab0541 | C13: 703430 | D13: 46014 | E13: 900219834 | F13: F2X S.A.S. | G13: 901907732 | H13: Tecnotics S.A.S | I13: 3361.35 | J13: 638.65 | K13: 0 | L13: 0 | M13: 0 | N13: 4000
... A24: Factura electrónica | B24: f5f77d4ac7f0c7f64966ffdf96e444d8914e46c20d461975e20b4e616502fbe33434afef8f84f6b4a0d20af4bf5e0e90 | C24: 883 | D24: 46010 | E24: 901649254 | F24: JSA DISTRIBUCIONES S.A.S. | G24: 901907732 | H24: TECNOTICS S.A.S. | I24: 1860083.6 | J24: 353415.88 | K24: 0 | L24: 0 | M24: 0 | N24: 2213499.5
A25: Factura electrónica | B25: bfb6492b1b4dcfa1697749cfd7a4e98e7ac345596f7f4cb993566495e8ce4d0558f06e3b8f7b7ae5e649e3a0c93ee08f | C25: 13206 | D25: 46010 | E25: 700108357 | F25: STEFANO ZINNO | G25: 901907732 | H25: tecnotics S.A.S. | I25: 235500 | J25: 0 | K25: 0 | L25: 0 | M25: 0 | N25: 235500 | O25: =+I25*3.5% -> 8242.5
A26: Factura electrónica | B26: c667311bba11f05ee0a408284e735fade9e833041d55eb2bce7eef4419c9fc195229683221f9027c81b5fe65d45a3888 | C26: 17846 | D26: 46010 | E26: 901476410 | F26: GRUPO LEDACOM SAS | G26: 901907732 | H26: TECNOTICS SAS | I26: 24706 | J26: 4694 | K26: 0 | L26: 0 | M26: 0 | N26: 29400 | O26: =+I26*2.5% -> 617.65
A27: Factura electrónica | B27: 17af339e7b8e6d79d6ec114bc963c755a1696df827b77c87671d6b1fbdd1fe745ce97108e33af4d1db2f2c1c5de81517 | C27: 874 | D27: 46009 | E27: 901649254 | F27: JSA DISTRIBUCIONES S.A.S. | G27: 901907732 | H27: TECNOTICS S.A.S. | I27: 3632352.8 | J27: 690147.04 | K27: 0 | L27: 0 | M27: 0 | N27: 4322499.9
A28: Factura electrónica | B28: 5cc10645d6fa08e426da11dd5ae7525a36fa5ef01e3a532966bdf03093318c88a6385b43842c73bf14ad5168af1c8fde | C28: 33384 | D28: 46008 | E28: 901161479 | F28: IDT COLOMBIA SAS | G28: 901907732 | H28: TECNOTICS SAS | I28: 2037560 | J28: 387136.4 | K28: 0 | L28: 0 | M28: 0 | N28: 2424696.4
A29: Factura electrónica | B29: a4b89aef16f675b32b5b37561dd7e98e2799be236e8e588b48664298280a247a7bb4a7de6bf924da22c4786951db3b67 | C29: 592685 | D29: 46008 | E29: 800091549 | F29: IMPRESISTEM S A S | G29: 901907732 | H29: TECNOTICS S.A.S. | I29: 1612896 | J29: 0 | K29: 0 | L29: 0 | M29: 0 | N29: 1612896
A30: Factura electrónica | B30: c8928927314f4ab63f8d04b887e99be5a61b1f85212c8ba9c0d34a540553c516e5d4aeff2a42dcea04e36b9e981b1253 | C30: 592620 | D30: 46008 | E30: 800091549 | F30: IMPRESISTEM S A S | G30: 901907732 | H30: TECNOTICS S.A.S. | I30: 311728 | J30: 0 | K30: 0 | L30: 0 | M30: 0 | N30: 311728
A31: Factura electrónica | B31: 8902454e8f65653647b70196e12a1c6c7f26dfd079d1b062d5f757acbc8c5de760eb478ddf8b9f8b8266431e6b840396 | C31: 592619 | D31: 46008 | E31: 800091549 | F31: IMPRESISTEM S A S | G31: 901907732 | H31: TECNOTICS S.A.S. | I31: 468383 | J31: 0 | K31: 0 | L31: 0 | M31: 0 | N31: 468383
A32: Factura electrónica | B32: 936fbeea12c8b3d8db4cc8560cd8dc3af4babfa992f7d1406d03b7e136b025c9669e366ec68bf0846da96ba8197ba39d | C32: 592618 | D32: 46008 | E32: 800091549 | F32: IMPRESISTEM S A S | G32: 901907732 | H32: TECNOTICS S.A.S. | I32: 548978 | J32: 0 | K32: 0 | L32: 0 | M32: 0 | N32: 548978
A33: Factura electrónica | B33: 5d85a4d682574ddd2fccf652aa7bb7a72704e8dfeb6a70549f873e347973b58fe59b9447edd5748d4b19dee7a935bf87 | C33: 592616 | D33: 46008 | E33: 800091549 | F33: IMPRESISTEM S A S | G33: 901907732 | H33: TECNOTICS S.A.S. | I33: 229559 | J33: 0 | K33: 0 | L33: 0 | M33: 0 | N33: 229559
A34: Factura electrónica | B34: e902586e468724baa9edf3198828b5babda7c8fc21eb03e4ed0449b0bff2ccf437753d64e3fe2025737708816a967e57 | C34: 592615 | D34: 46008 | E34: 800091549 | F34: IMPRESISTEM S A S | G34: 901907732 | H34: TECNOTICS S.A.S. | I34: 135780 | J34: 0 | K34: 0 | L34: 0 | M34: 0 | N34: 135780
A35: Factura electrónica | B35: 2ecb4b0dd903a151cb1d8f902887b62e5dd5702e7bb2d1c937d3eb2494872bc639a915c5cf8b9823951750d85d6ec6dc | C35: 592614 | D35: 46008 | E35: 800091549 | F35: IMPRESISTEM S A S | G35: 901907732 | H35: TECNOTICS S.A.S. | I35: 23266 | J35: 0 | K35: 0 | L35: 0 | M35: 0 | N35: 23266
A36: Factura electrónica | B36: 1ab8767e4d089fdfb38c23fc5cb39a184f0c6bd75d49c2999870943ff6d4666f634e74e97cc570ad72607859e2d03ebf | C36: 592612 | D36: 46008 | E36: 800091549 | F36: IMPRESISTEM S A S | G36: 901907732 | H36: TECNOTICS S.A.S. | I36: 332984 | J36: 0 | K36: 0 | L36: 0 | M36: 0 | N36: 332984
A37: Factura electrónica | B37: 96fbd8d6a63b72e65f74927a50984d8283be221b2fbbd25c319fb840cf9599770dcff690cd2e3c647c82a213a64591f1 | C37: 592611 | D37: 46008 | E37: 800091549 | F37: IMPRESISTEM S A S | G37: 901907732 | H37: TECNOTICS S.A.S. | I37: 763843 | J37: 0 | K37: 0 | L37: 0 | M37: 0 | N37: 763843
A38: Factura electrónica | B38: c259c6c915e70f1e1a6a4aca7e24eb5d1e8bf2c0da3b6819d0042501bd39298cc74d07b17bd50798fcee2ae4bba7e0b5 | C38: 592610 | D38: 46008 | E38: 800091549 | F38: IMPRESISTEM S A S | G38: 901907732 | H38: TECNOTICS S.A.S. | I38: 127294 | J38: 0 | K38: 0 | L38: 0 | M38: 0 | N38: 127294
... A52: Factura electrónica | B52: 90ed1b2adaef48716c4f3be5946c63162ca0b5ec484077b94814c93b4f90fd26b345627d48df1f453a59e3efc68c1d05 | C52: 150179 | D52: 46003 | E52: 811000784 | F52: TERMINAL SUR DE MEDELLIN PH | G52: 901907732 | H52: TECNO TIC SAS | I52: 3529.41 | J52: 670.59 | K52: 0 | L52: 0 | M52: 0 | N52: 4200
A53: Factura electrónica | B53: f33d71968fa3b5e0bd4b52ef2838a2698ab87c56e1c2dd5eb34463920ecdb80d56e21959761a8c14728a3eaffa79a685 | C53: 198799 | D53: 46003 | E53: 901192317 | F53: SYSCOM COLOMBIA SAS | G53: 901907732 | H53: TECNOTICS SAS | I53: 534715.61 | J53: 101597 | K53: 0 | L53: 0 | M53: 0 | N53: 636312.61 | O53: =+I53*2.5% -> 13367.89
A54: Factura electrónica | B54: e97b2622cf247aeb997f7ae817f354872d23666564a78ee718bbf5272c3a9035dde74f32b0e5aa21601ff90e83228df8 | C54: 13184 | D54: 46003 | E54: 700108357 | F54: STEFANO ZINNO | G54: 901907732 | H54: tecnotics S.A.S. | I54: 159000 | J54: 0 | K54: 0 | L54: 0 | M54: 0 | N54: 159000 | O54: =+I54*3.5% -> 5565
A55: Factura electrónica | B55: 9037cab86c844c2cf159c07723bf8efbdf2734f112aced6702905349d82882ab4f600a75f24d4da1e51cf3831957fa61 | C55: 849 | D55: 46003 | E55: 901649254 | F55: JSA DISTRIBUCIONES S.A.S. | G55: 901907732 | H55: TECNOTICS S.A.S. | I55: 7563024 | J55: 1436974.6 | K55: 0 | L55: 0 | M55: 0 | N55: 8999998.6
A56: Factura electrónica | B56: c994bfd9927ab394e2343ebc2367f882916674edd14c9bb82f1e2b1780c54b041127289165952b1adff8ca1bfa657be7 | C56: 464594 | D56: 46002 | E56: 900219834 | F56: F2X S.A.S. | G56: 901907732 | H56: Tecnotics S.A.S | I56: 3781.51 | J56: 718.49 | K56: 0 | L56: 0 | M56: 0 | N56: 4500
A57: Factura electrónica | B57: d812e3801c68f1f5630ec0d5820487cf4af75417d50efa9c60177143bd2bcbf41d5644266c695f1a9ef06d23d8df0992 | C57: 163535970 | D57: 46002 | E57: 830114921 | F57: COLOMBIA MOVIL S.A. ESP | G57: 901907732 | H57: TECNOTICS SAS | I57: 6302.59 | J57: 1197.41 | K57: 0 | L57: 0 | M57: 0 | N57: 7500
A58: Factura electrónica | B58: 1647e4bed00eb05f04bc0cf236bc827697dca663b2cb13ebdb369978a481ffc34bf9847de10f01f692afcb043050eaa1 | C58: 8886341 | D58: 46001 | E58: 900219834 | F58: F2X S.A.S. | G58: 901907732 | H58: Tecnotics S.A.S | I58: 3739.51 | J58: 710.49 | K58: 0 | L58: 0 | M58: 0 | N58: 4450
A59: Factura electrónica | B59: 5dc4f16893dcf903e0957949789752cf4ffa842d82d0c4eb50dbf1ee287dd9c75ed3f150a649711d1074f2359973c924 | C59: 437529 | D59: 46001 | E59: 900219834 | F59: F2X S.A.S. | G59: 901907732 | H59: Tecnotics S.A.S | I59: 6554.62 | J59: 1245.38 | K59: 0 | L59: 0 | M59: 0 | N59: 7800
A60: Factura electrónica | B60: a41198a53630897ff7bc481d2642cbd3212210998441d4f4f2e0c3898a955c86fbbdd7aff44fe05e554142eb52d798fa | C60: 208497 | D60: 45997 | E60: 890941794 | F60: FRANCISCO MURILLO S.A.S. | G60: 901907732 | H60: TECNOTICS SAS | I60: 215500 | J60: 40945 | K60: 0 | L60: 0 | M60: 0 | N60: 256445
A61: Factura electrónica | B61: 7d1d8210918fdaff3e839a75d4df02037e85d4a4f39f4517200846fd05d61f4a4d3b016e5758c27b33dc905a2ba5d8c2 | C61: 4320 | D61: 45997 | E61: 901421223 | F61: ILUMINACIONES ANTIOQUIA SAS | G61: 901907732 | H61: TECNOTICS SAS | I61: 151260.5 | J61: 28739.5 | K61: 0 | L61: 0 | M61: 0 | N61: 180000
A62: Factura electrónica | B62: 26c7122f3f5128f21b819210525a384920961e6181bb13284a5b53a13a61e2cffaa28eadae7099db07337501c6ff4a21 | C62: 362477 | D62: 45996 | E62: 900219834 | F62: F2X S.A.S. | G62: 901907732 | H62: Tecnotics S.A.S | I62: 5042.02 | J62: 957.98 | K62: 0 | L62: 0 | M62: 0 | N62: 6000
A63: Factura electrónica | B63: c2bfd1fbcafe97515ac8d69ddcd40f81e7548b190390b800cdf5cc277a747bc4d02ec0ac04b8e6e5d0b71d6438af9d92 | C63: 36051 | D63: 45996 | E63: 901051870 | F63: D4 FIT WEAR S.A.S | G63: 901907732 | H63: Alejandro Martinez | I63: 112689.08 | J63: 4310.92 | K63: 0 | L63: 0 | M63: 0 | N63: 117000
A64: Factura electrónica | B64: 8d4bb90e1d62b4651db49bc3556cb8e2244febc1c3081be353cb71e7701cf27e4bfc3d2ff520407d9daf98b273af458a | C64: 13129 | D64: 45996 | E64: 700108357 | F64: STEFANO ZINNO | G64: 901907732 | H64: tecnotics S.A.S. | I64: 218000 | J64: 0 | K64: 0 | L64: 0 | M64: 0 | N64: 218000 | O64: =+I64*3.5% -> 7630
A65: Factura electrónica | B65: f905502b57abc4c0c8681fc0ab1b9c5dd83f16686bd75732ec28da6ac9fa119ed17191df208e7d393e4c01537d2abf31 | C65: 36004 | D65: 45996 | E65: 901051870 | F65: D4 FIT WEAR S.A.S | G65: 901907732 | H65: Alejandro Martinez | I65: 112689.08 | J65: 4310.92 | K65: 0 | L65: 0 | M65: 0 | N65: 117000
A66: Factura electrónica | B66: 2d87371b5868f6b6f4c3c416998bbc7b02c452c89c2512da15af543f78dd04bca413fdc4b4c1a0448e7d9133315a6b5f | C66: 1282 | D66: 45996 | E66: 93397337 | F66: KLEYMAN YONATHAN VERGARA GONZALEZ | G66: 901907732 | H66: TECNOTICS SAS | I66: 100000 | J66: 0 | K66: 0 | L66: 0 | M66: 0 | N66: 100000
A67: Factura electrónica | B67: 77f8307d65d58fc025c7d7078412753ebbf8bfd0415f7b8c7bfe8d8695834f54dbd06466c46b61fcc896f46608922b10 | C67: 318572 | D67: 45994 | E67: 900219834 | F67: F2X S.A.S. | G67: 901907732 | H67: Tecnotics S.A.S | I67: 3277.31 | J67: 622.69 | K67: 0 | L67: 0 | M67: 0 | N67: 3900
A68: Factura electrónica | B68: fa4c3b1c02bb810aa695959c2ae952af7738f741d27bf7dcddc7944aef8812bb5deb0563864b993752b6195a8f971619 | C68: 208027 | D68: 45994 | E68: 890941794 | F68: FRANCISCO MURILLO S.A.S. | G68: 901907732 | H68: TECNOTICS SAS | I68: 568459 | J68: 108007.21 | K68: 0 | L68: 0 | M68: 0 | N68: 676466.21 | O68: =+I68*2.5% -> 14211.475
A69: Factura electrónica | B69: 4197b184ea544479bde5310cb35f641b4736843e70cbc531a9ee2bbc7bec76739c1e3ae275b68b128e95a00f4c1897d9 | C69: 80249 | D69: 45994 | E69: 830085336 | F69: DIGITAL MTX SAS | G69: 901907732 | H69: TECNOTICS S.A.S | I69: 88235.29 | J69: 16764.71 | K69: 0 | L69: 0 | M69: 0 | N69: 105000
A70: Factura electrónica | B70: 5c13c11fac47264a5a538fb7231e31e0f7e3aceb1a099851ec9f660e0d96c6e2184d64959d5bca5cdd1687c32cbd9a81 | C70: 15766 | D70: 45994 | E70: 900594706 | F70: PAPELES Y TINTAS PUNTO CLAVE SAS | G70: 901907732 | H70: TECNOTICS SAS | I70: 113446 | J70: 21554.74 | K70: 0 | L70: 0 | M70: 0 | N70: 135000.74
A71: Factura electrónica | B71: f25fbb152f3badd5ce03e11c3bf451e39853ba5f9c1a1be013a7e93f330fb1ec8a0f35174d41a61a15400f9d8d199b9f | C71: 7723 | D71: 45993 | E71: 900762275 | F71: GLOBAL-TEC S.A.S | G71: 901907732 | H71: TECNOTICS SAS | I71: 159797.82 | J71: 0 | K71: 0 | L71: 0 | M71: 0 | N71: 159797.82
A72: Factura electrónica | B72: 64d931e3c9e270e41c58c3e010ae04a40be0d05b90460cd060a195b2ef225360a76e84a45fd3c7cf540914c28378bede | C72: 7722 | D72: 45993 | E72: 900762275 | F72: GLOBAL-TEC S.A.S | G72: 901907732 | H72: TECNOTICS SAS | I72: 705150 | J72: 0 | K72: 0 | L72: 0 | M72: 0 | N72: 705150
A73: Factura electrónica | B73: 73deee88350617a3e3509d206a415cf0285d798b7415613771e10a92d68b829165ccdbcb2a95509d8c1e9c9dfc581b89 | C73: 304532 | D73: 45993 | E73: 900219834 | F73: F2X S.A.S. | G73: 901907732 | H73: Tecnotics S.A.S | I73: 3781.51 | J73: 718.49 | K73: 0 | L73: 0 | M73: 0 | N73: 4500
A74: Factura electrónica | B74: 2dc5fd2d1cdeee5ce9f6d4bc40578ac014551d62442c6986cccf62a934cf1e11ce09c92e9becf4c5ba0a3ad6e46df164 | C74: 594039 | D74: 45991 | E74: 900188685 | F74: ELECTROSERVIMOS S.A. | G74: 901907732 | H74: TECNOTICS SAS | I74: 368204 | J74: 69958.76 | K74: 0 | L74: 0 | M74: 0 | N74: 438162.76
A75: Factura electrónica | B75: f6110434af3a6cfc8006ada3f4a9f718add56e12ec089a1c8d54f038142865e9ffc8012beb5639b2651349aa0e266a46 | C75: 38739 | D75: 45983 | E75: 900219834 | F75: F2X S.A.S. | G75: 901907732 | H75: Tecnotics S.A.S | I75: 4600 | J75: 0 | K75: 0 | L75: 0 | M75: 0 | N75: 4600
A76: Nota de crédito electrónica | B76: 82acda9f3532a022d6ea2bf739a2687663b608fb89d77511261fe4d7a58eabba8f50001f0754d327222dff0323d78d8a | C76: DENC4196257 | D76: 45990 | E76: 900219834 | F76: F2X S.A.S. | G76: 901907732 | H76: Tecnotics S.A.S | I76: -4600 | J76: 0 | K76: 0 | L76: 0 | M76: 0 | N76: -4600
A77: Factura electrónica | B77: d5fe946b4eaaa341eff94e7940aa59f3aa1e3bc38ede1786cd3320310e36295bcb0eef82130cc3e03aefbc2ccfc66249 | C77: 13086 | D77: 45990 | E77: 700108357 | F77: STEFANO ZINNO | G77: 901907732 | H77: tecnotics S.A.S. | I77: 273000 | J77: 0 | K77: 0 | L77: 0 | M77: 0 | N77: 273000 | O77: =+I77*3.5% -> 9555
A78: Factura electrónica | B78: c29f9c3d738295b5248829de82576ce71e86d487bd65eeb7077934e108e15255ceb6d24b57021c76b93bc55858577e97 | C78: 147918 | D78: 45989 | E78: 900219834 | F78: F2X S.A.S. | G78: 901907732 | H78: Tecnotics S.A.S | I78: 3361.34 | J78: 638.66 | K78: 0 | L78: 0 | M78: 0 | N78: 4000
A79: Factura electrónica | B79: 988c958a2ebabc6ec63b27a927d5488cdb45e3a440472f1c654fc85420e9c1abec09e9b096e1416ad0f8c605fc4d7788 | C79: 183730 | D79: 45988 | E79: 900378652 | F79: JAL TECH SOLUCIONES S.A.S | G79: 901907732 | H79: TECNOTICS SAS | I79: 293620.17 | J79: 55787.83 | K79: 0 | L79: 0 | M79: 0 | N79: 349408
A80: Factura electrónica | B80: 07a88b8e924f8e5b69bac9ced6d6e24a2217cd17e9c5a032b44677793412e4952d4d1d0c68730ce50b6ce62afef6e3ff | C80: 111476 | D80: 45988 | E80: 901237330 | F80: SIGMAPLASTICOS MEDELLIN SAS | G80: 901907732 | H80: TECNOTICS SAS | I80: 129453.79 | J80: 24596.22 | K80: 0 | L80: 0 | M80: 0 | N80: 154050.01
A81: Factura electrónica | B81: f70049400f62db71ef0af0ffbb0a0ca6ddc3b13b9bbce9439da27821d128fee77b2623864466046fe675589338849b6d | C81: 111102 | D81: 45988 | E81: 900219834 | F81: F2X S.A.S. | G81: 901907732 | H81: Tecnotics S.A.S | I81: 7800 | J81: 0 | K81: 0 | L81: 0 | M81: 0 | N81: 7800
A82: Factura electrónica | B82: 9c7bf991a2bb0b4e5a24c304102ae9fd0d17a4d9d995952ec65e357175b4b8c96d89e8a83d6c46c6c0d234e478d0da6d | C82: 206735 | D82: 45983 | E82: 890941794 | F82: FRANCISCO MURILLO S.A.S. | G82: 901907732 | H82: TECNOTICS SAS | I82: 18280 | J82: 3473.2 | K82: 0 | L82: 0 | M82: 0 | N82: 21753.2
A83: Factura electrónica | B83: fae4a5fd29b95a1f2ed23ad55feb1532513dbb589ffa0ba9ddd11993b4d4a8f7c84f36c1af6a827cdf602d237e9c3f1f | C83: 160356228 | D83: 45983 | E83: 830114921 | F83: COLOMBIA MOVIL S.A. ESP | G83: 901907732 | H83: TECNOTICS SAS | I83: 97975.78 | J83: 18615.39 | K83: 0 | L83: 1848.83 | M83: 0 | N83: 118440
A84: Factura electrónica | B84: 6b91e63dcecf4d650122a36b252aa0a5021f3ddb061e7f4ba7930edf1bdecd31acdd55d750be30e442017379633a57df | C84: 13050 | D84: 45982 | E84: 700108357 | F84: STEFANO ZINNO | G84: 901907732 | H84: tecnotics S.A.S. | I84: 215000 | J84: 0 | K84: 0 | L84: 0 | M84: 0 | N84: 215000 | O84: =+I84*3.5% -> 7525
A85: Factura electrónica | B85: 07bcab9a62c333febecfa0f03ebb0b8ceddaeaeefadba82f330ed78f118c1a8ad31649933476047ab1e7c1675990da93 | C85: 230429 | D85: 45982 | E85: 900276962 | F85: D1 S A S | G85: 901907732 | H85: Tecnotics sas | I85: 73903.36 | J85: 12806.63 | K85: 0 | L85: 0 | M85: 0 | N85: 86709.99
A86: Factura electrónica | B86: 24cabce0fdaf132d26d8b4a45b4a93bd4e900c1df2ceb59abd4770659ff0026e4595c67ab8f82cffb22c3eb3655f5015 | C86: 160205561 | D86: 45982 | E86: 830114921 | F86: COLOMBIA MOVIL S.A. ESP | G86: 901907732 | H86: TECNOTICS SAS TECNOTICS SAS | I86: 10.94 | J86: 2.06 | K86: 0 | L86: 0 | M86: 0 | N86: 13
A87: Factura electrónica | B87: fbac05624022b61b88dda6e5b5e90502f1ad36369075aec59f14397db26f33a898a8b85f28c1f2e1d7b81e7335e75b93 | C87: 160205433 | D87: 45981 | E87: 830114921 | F87: COLOMBIA MOVIL S.A. ESP | G87: 901907732 | H87: TECNOTICS SAS | I87: 68529.85 | J87: 13020.61 | K87: 0 | L87: 1188.54 | M87: 0 | N87: 82739
A88: Factura electrónica | B88: 7d8c0079864b215c675ec3a83c397a01c4c9968bc03ab60931f5663eb8456502240ffa280c71979a937378689c659c39 | C88: 585267 | D88: 45981 | E88: 800091549 | F88: IMPRESISTEM S A S | G88: 901907732 | H88: TECNOTICS S.A.S. | I88: 1526740 | J88: 0 | K88: 0 | L88: 0 | M88: 0 | N88: 1526740
A89: Factura electrónica | B89: e9225227be19fb9411a653c1e3619137035ab6a32edc310f391bf7a72a4669f045f6fdc5bb92c6b59c0738de0c255943 | C89: 206405 | D89: 45981 | E89: 890941794 | F89: FRANCISCO MURILLO S.A.S. | G89: 901907732 | H89: TECNOTICS SAS | I89: 186920 | J89: 35514.8 | K89: 0 | L89: 0 | M89: 0 | N89: 222434.8
A90: Factura electrónica | B90: e0646912f0699ebf8f98f2338f4a303464ed677cd2063f56d829492fa4e6b70dc6b4fa54f6128d0cb8163a8ec943e35b | C90: 117010 | D90: 45980 | E90: 900584970 | F90: Grupo Control de Colombia S.A.S | G90: 901907732 | H90: TECNOTICS SAS | I90: 1305255 | J90: 247998 | K90: 0 | L90: 0 | M90: 0 | N90: 1553253 | O90: =+I90*2.5% -> 32631.375
A91: Factura electrónica | B91: 78d823d5851ec31bc7e37ce20225866127c2dc5e87fafdd3ecb2f3f1b7f36b8dca65a209ca06084da2b5e3a82bb57042 | C91: 195378 | D91: 45980 | E91: 901192317 | F91: SYSCOM COLOMBIA SAS | G91: 901907732 | H91: TECNOTICS SAS | I91: 251462.21 | J91: 47778 | K91: 0 | L91: 0 | M91: 0 | N91: 299240.21
A92: Factura electrónica | B92: 03f820e3f02746b026fd344a3e3220749df12f746dd2ad8efad3a8b0bc5411db6a07f8aa316b8a798b89ddba13682332 | C92: 105013749 | D92: 45980 | E92: 900059238 | F92: MAKRO SUPERMAYORISTA S.A.S | G92: 901907732 | H92: TECNOTICS SAS. | I92: 106890.72 | J92: 20309.28 | K92: 0 | L92: 0 | M92: 0 | N92: 127200
A93: Factura electrónica | B93: a435837eaea3cb2162860409bd4f8d341e93ca134a10f8a1f3af7a048d9b8fbe022e9a2f1cb16346d3f25640d0f00738 | C93: 109810 | D93: 45980 | E93: 901237330 | F93: SIGMAPLASTICOS MEDELLIN SAS | G93: 901907732 | H93: TECNOTICS SAS | I93: 213193.2 | J93: 40506.71 | K93: 0 | L93: 0 | M93: 0 | N93: 253699.91
A94: Factura electrónica | B94: 6d6f5b976ad5f5998fbad7aeae7418a91e68a4726120e9baa570ee03e9c33125a8a8b5a43f67977f2ae88612bc2bcbb2 | C94: 109777 | D94: 45980 | E94: 901237330 | F94: SIGMAPLASTICOS MEDELLIN SAS | G94: 901907732 | H94: TECNOTICS SAS | I94: 99915.97 | J94: 18984.03 | K94: 0 | L94: 0 | M94: 0 | N94: 118900
A95: Factura electrónica | B95: b4803fe7ca92a8659f8a8d9f4f52b32e1ffce30a14551d960b2e657b2dc544e4f719c9a76693bb1ac2c9fad8849485b6 | C95: 6607 | D95: 45980 | E95: 70780282 | F95: JOSE ANGEL LOPEZ VILLA | G95: 901907732 | H95: TECNOTICS SAS | I95: 16000 | J95: 0 | K95: 0 | L95: 0 | M95: 0 | N95: 16000
A96: Factura electrónica | B96: fa2412ce2f7cbdb5bd8addf53778e4b008de298640d4051d5dbe9ffb3aaf6aedc8e560ced82fbf5ec488d68251da575a | C96: 143188 | D96: 45980 | E96: 811000784 | F96: TERMINAL SUR DE MEDELLIN PH | G96: 901907732 | H96: TECNO TIC SAS | I96: 104201.68 | J96: 19798.32 | K96: 0 | L96: 0 | M96: 0 | N96: 124000
A97: Factura electrónica | B97: 71ae7d0d62146ef47073be5fccc78f4b841d9258677de583fe2929f0168535b58bb9b022e986c3fd329c992b546d9441 | C97: 30287 | D97: 45980 | E97: 900459737 | F97: GRUPO EDS AUTOGAS S.A.S | G97: 901907732 | H97: TECNOTICS SAS | I97: 225686 | J97: 0 | K97: 0 | L97: 0 | M97: 0 | N97: 225686
A98: Factura electrónica | B98: 7fb0fcdee64994a17f1ddaaa5473a11be8c7667a2480b3f2a9a00ec4b00964c66e10c15b4dc7de005bdea8e04e1072f0 | C98: 8282539 | D98: 45978 | E98: 900219834 | F98: F2X S.A.S. | G98: 901907732 | H98: Tecnotics S.A.S | I98: 3361.34 | J98: 638.66 | K98: 0 | L98: 0 | M98: 0 | N98: 4000
A99: Factura electrónica | B99: 45c8dc7e32eb7b3a34d50637d0a691a89b8e0996af84707587a5cc4cc90abe7578df561ae25fdd676017875ce67d5019 | C99: 270895 | D99: 45977 | E99: 900188685 | F99: ELECTROSERVIMOS S.A. | G99: 901907732 | H99: TECNOTICS SAS | I99: 133395 | J99: 25345.05 | K99: 0 | L99: 0 | M99: 0 | N99: 158740.05
A100: Factura electrónica | B100: 8e1deff359effb3e3184d48f4e26ee10780650fb5200c6a0693ef1b682abb6b2f92c2ab9ee9d8cd97d72f16b88c31613 | C100: 13030 | D100: 45975 | E100: 700108357 | F100: STEFANO ZINNO | G100: 901907732 | H100: tecnotics S.A.S. | I100: 276000 | J100: 0 | K100: 0 | L100: 0 | M100: 0 | N100: 276000 | O100: =+I100*3.5% -> 9660
A101: Factura electrónica | B101: 94d58ba9393dbd2a063b366e9a5e46a4c1bb81c3e5bc8fa46015c60bd749c2d8daf98b4659028b97a70b45daeb1a2adc | C101: 110013947 | D101: 45975 | E101: 900059238 | F101: MAKRO SUPERMAYORISTA S.A.S | G101: 901907732 | H101: TECNOTICS SAS. | I101: 42848.73 | J101: 8141.27 | K101: 0 | L101: 0 | M101: 0 | N101: 50990
A102: Factura electrónica | B102: e151a24a0dadd3c2388e8701f55f98d0868926830e1c06d1982345f63d1fb008ffa12352df3ac0ddd94f47a2f753b8a4 | C102: 79548 | D102: 45975 | E102: 830085336 | F102: DIGITAL MTX SAS | G102: 901907732 | H102: TECNOTICS S.A.S | I102: 145378.15 | J102: 27621.84 | K102: 0 | L102: 0 | M102: 0 | N102: 172999.99
A103: Factura electrónica | B103: cd16537f96b6d6561536adc5f26e5bba1905b63098e15f59bd2c7aeec89759eceeaf5a3b1cb89e41f523a70777aa651d | C103: 11797 | D103: 45975 | E103: 901476410 | F103: GRUPO LEDACOM SAS | G103: 901907732 | H103: TECNOTICS SAS | I103: 1537815 | J103: 292185 | K103: 0 | L103: 0 | M103: 0 | N103: 1830000 | O103: =+I103*2.5% -> 38445.375
A104: Factura electrónica | B104: 006eb63072755ce169153f839b0ff4c539ec91d8d779e9901939ff12f9da4768fac7524715063a94bf44985433e63d05 | C104: 2439 | D104: 45975 | E104: 800157387 | F104: COMERCIALIZADORA MINIDELICIAS S.A.S. | G104: 901907732 | H104: TECNOTICS SAS | I104: 38133.33 | J104: 0 | K104: 0 | L104: 1466.67 | M104: 0 | N104: 39600
A105: Factura electrónica | B105: 64d364a4fbf85771e860d9504d1e993d893dc1221d6add65d1667574b252c2e440b24f7aa0e1b1baf49746f244ed0e07 | C105: 583620 | D105: 45974 | E105: 800091549 | F105: IMPRESISTEM S A S | G105: 901907732 | H105: TECNOTICS S.A.S. | I105: 460476 | J105: 0 | K105: 0 | L105: 0 | M105: 0 | N105: 460476
A106: Factura electrónica | B106: 232dfeab2126a923acced1199a64dd4c9be3643d718d3f5e7c9d3babb1c70a3c915e6975ef08635df08d3675ce9b4d9e | C106: 194725 | D106: 45974 | E106: 901192317 | F106: SYSCOM COLOMBIA SAS | G106: 901907732 | H106: TECNOTICS SAS | I106: 479747.12 | J106: 91153 | K106: 0 | L106: 0 | M106: 0 | N106: 570900.12
A107: Factura electrónica | B107: f8327e619e1e38669f87ed493a7582c9815636d6edfc012737272913a96f3865b1ff02ca3b86d2e7c468482dca55ef4e | C107: 194722 | D107: 45974 | E107: 901192317 | F107: SYSCOM COLOMBIA SAS | G107: 901907732 | H107: TECNOTICS SAS | I107: 1602896.9 | J107: 304551 | K107: 0 | L107: 0 | M107: 0 | N107: 1907447.9 | O107: =+I107*2.5% -> 40072.423
A108: Factura electrónica | B108: 31c8116a4e02209f9fb3cb2bb2b61e893814ae7303de8449727916b03225d0a9f692220436221acc99a001888009409f | C108: 336260 | D108: 45974 | E108: 900471052 | F108: EPAYCO.COM S.A.S | G108: 901907732 | H108: TECNOTISC SAS | I108: 69900 | J108: 0 | K108: 0 | L108: 0 | M108: 0 | N108: 69900
A109: Factura electrónica | B109: 08aebcd36edd0f1861cdb8d520ff578b519b54f03a258a4b94c5b1533e0232d977ee19bda47686dd673fd54a40a986f0 | C109: 32014 | D109: 45974 | E109: 901161479 | F109: IDT COLOMBIA SAS | G109: 901907732 | H109: TECNOTICS SAS | I109: 1485980 | J109: 282336.2 | K109: 0 | L109: 0 | M109: 0 | N109: 1768316.2
A110: Factura electrónica | B110: 494000b5a54aca7d251558633f5a5f5a44b27a0b49250d6b6f60c608d4aba134b14328184670095287f4d757fb874c7a | C110: 582928 | D110: 45973 | E110: 800091549 | F110: IMPRESISTEM S A S | G110: 901907732 | H110: TECNOTICS S.A.S. | I110: 746734 | J110: 0 | K110: 0 | L110: 0 | M110: 0 | N110: 746734
A111: Factura electrónica | B111: 8035035493f497c0fa88b22f9d9154deaee5ab58ffb7a5ec3fedb4ae105213fcb2d96a8e49547e1ac175b472426df1fd | C111: 582927 | D111: 45973 | E111: 800091549 | F111: IMPRESISTEM S A S | G111: 901907732 | H111: TECNOTICS S.A.S. | I111: 440474 | J111: 0 | K111: 0 | L111: 0 | M111: 0 | N111: 440474
A112: Factura electrónica | B112: 8708fd6602ce70a6bd1aa4e419d4e7a3ed1152aa23414e5ae6ed67a3ab362cbb08fe7bf08c7e03c45bd14f2bd427e0ba | C112: 582926 | D112: 45973 | E112: 800091549 | F112: IMPRESISTEM S A S | G112: 901907732 | H112: TECNOTICS S.A.S. | I112: 22746 | J112: 0 | K112: 0 | L112: 0 | M112: 0 | N112: 22746
A113: Factura electrónica | B113: 0d0108815472f245f2c4433a896cc5b5324e8c7276bbf2002ddee030d72be67b6c6ca58cade9ecfc012520df28ea0e00 | C113: 582858 | D113: 45973 | E113: 800091549 | F113: IMPRESISTEM S A S | G113: 901907732 | H113: TECNOTICS S.A.S. | I113: 817866 | J113: 0 | K113: 0 | L113: 0 | M113: 0 | N113: 817866
A114: Factura electrónica | B114: 8ec6d1204928f64b2a28948230a339e02bc1b953e0ce95ef4a119067a61e17219776d46ce7e42c4092c6ce43fcd847bc | C114: 582856 | D114: 45973 | E114: 800091549 | F114: IMPRESISTEM S A S | G114: 901907732 | H114: TECNOTICS S.A.S. | I114: 304745 | J114: 0 | K114: 0 | L114: 0 | M114: 0 | N114: 304745
A115: Factura electrónica | B115: 333483f5d046b4a5796c17b4d733036d1ff61942b099ee135e727abbb1989caaecbe9842be19f56d89eb9f1ad140ae06 | C115: 582855 | D115: 45973 | E115: 800091549 | F115: IMPRESISTEM S A S | G115: 901907732 | H115: TECNOTICS S.A.S. | I115: 536681 | J115: 0 | K115: 0 | L115: 0 | M115: 0 | N115: 536681
A116: Factura electrónica | B116: 44661d96dd13f06547af312c48b4dd0aa052f468b13dc1a4482541fa5c8897c087eb38dd69dceade16e89e2e8dfa28a3 | C116: 582854 | D116: 45973 | E116: 800091549 | F116: IMPRESISTEM S A S | G116: 901907732 | H116: TECNOTICS S.A.S. | I116: 224417 | J116: 0 | K116: 0 | L116: 0 | M116: 0 | N116: 224417
A117: Factura electrónica | B117: 22f48b845f9eb9a38ea381ed19937d58019950f8bafe092529ece1e70c0fe00c3d146d4f42272216b96094774c4b0b2a | C117: 582853 | D117: 45973 | E117: 800091549 | F117: IMPRESISTEM S A S | G117: 901907732 | H117: TECNOTICS S.A.S. | I117: 132738 | J117: 0 | K117: 0 | L117: 0 | M117: 0 | N117: 132738
A118: Factura electrónica | B118: d9d70cf9340ddad8a078c802e3a67266a98d710d8912737a942b5aaec265752238f930162e43ddb6d314dbf95ef692ee | C118: 582852 | D118: 45973 | E118: 800091549 | F118: IMPRESISTEM S A S | G118: 901907732 | H118: TECNOTICS S.A.S. | I118: 325527 | J118: 0 | K118: 0 | L118: 0 | M118: 0 | N118: 325527
A119: Factura electrónica | B119: 68811b1d4dcc48ecad4b7712635ffac86f8b724ff28748970d7c8408775772feda4af6df22ea7289628d2c4aede74d48 | C119: 582851 | D119: 45973 | E119: 800091549 | F119: IMPRESISTEM S A S | G119: 901907732 | H119: TECNOTICS S.A.S. | I119: 3038808 | J119: 0 | K119: 0 | L119: 0 | M119: 0 | N119: 3038808
... A121: Factura electrónica | B121: c218b85fd0c8bc35a9f24f2d423be3a09024fd251bc70b6b9d9391d71e15491e9302db4b8f6b22d3b57eefda71e28c5a | C121: 582848 | D121: 45973 | E121: 800091549 | F121: IMPRESISTEM S A S | G121: 901907732 | H121: TECNOTICS S.A.S. | I121: 790111 | J121: 0 | K121: 0 | L121: 0 | M121: 0 | N121: 790111
A122: Factura electrónica | B122: cf8968d670273eefe8378dc351d6fa112d929c38c8b1ec42e69c717d4038b4ce6248d92be27be099e7e6b20cf7f06659 | C122: 10425 | D122: 45972 | E122: 901098244 | F122: SIMBA SOFTWARE SAS | G122: 901907732 | H122: TECNOTICS SAS | I122: 500000 | J122: 0 | K122: 0 | L122: 0 | M122: 0 | N122: 500000 | O122: =+I122*3.5% -> 17500
A123: Factura electrónica | B123: 8b93ab6848f164898e6e858e3e118b82aa120e09364063a7ece86dfec9f16e551be163df34e94cf3dcd7fe0a7f250ee2 | C123: 7575 | D123: 45972 | E123: 901519900 | F123: DISTRITRINI S.A.S. | G123: 901907732 | H123: TECNOTICS SAS | I123: 17000 | J123: 0 | K123: 0 | L123: 0 | M123: 0 | N123: 17000
A124: Factura electrónica | B124: 23ab676d89e2ba7d0f12cd96a215d0fc16b85cb5c00baab7bc1096cc2a55a7edb382b3262a18b9b8c6426e8cfad9f396 | C124: 158606264 | D124: 45972 | E124: 830114921 | F124: COLOMBIA MOVIL S.A. ESP | G124: 901907732 | H124: TECNOTICS SAS | I124: 49349.23 | J124: 9376.35 | K124: 0 | L124: 924.42 | M124: 0 | N124: 59650
...

Sheet Análisis Costos
A1: ANÁLISIS DE COSTOS MENSUALES — TECNOTICS S.A.S.
A2: Fuente: hoja Costos (facturas de compra, feb–dic 2025). Valores en COP.
A4: Mes | B4: # Facturas | C4: Subtotal | D4: IVA | E4: Total | F4: % del Total | H4: Top 10 Proveedores | I4: NIT | J4: # Facturas | K4: Total | L4: % del Total
A5: =DATE(2025,2,1) -> 45689 | B5: =COUNTIFS(Costos!$D:$D,">="&A5,Costos!$D:$D,"<"&EDATE(A5,1)) -> 15 | C5: =SUMIFS(Costos!$I:$I,Costos!$D:$D,">="&A5,Costos!$D:$D,"<"&EDATE(A5,1)) -> 13646284 | D5: =SUMIFS(Costos!$J:$J,Costos!$D:$D,">="&A5,Costos!$D:$D,"<"&EDATE(A5,1)) -> 0 | E5: =SUMIFS(Costos!$N:$N,Costos!$D:$D,">="&A5,Costos!$D:$D,"<"&EDATE(A5,1)) -> 13646284 | F5: =IFERROR(E5/$E$16,0) -> 0.035534878 | H5: IMPRESISTEM S A S | I5: 800091549 | J5: =COUNTIFS(Costos!$E:$E,I5) -> 162 | K5: =SUMIFS(Costos!$N:$N,Costos!$E:$E,I5) -> 166259481 | L5: =IFERROR(K5/$E$16,0) -> 0.43293913
A6: =EDATE(A5,1) -> 45717 | B6: =COUNTIFS(Costos!$D:$D,">="&A6,Costos!$D:$D,"<"&EDATE(A6,1)) -> 28 | C6: =SUMIFS(Costos!$I:$I,Costos!$D:$D,">="&A6,Costos!$D:$D,"<"&EDATE(A6,1)) -> 20366241 | D6: =SUMIFS(Costos!$J:$J,Costos!$D:$D,">="&A6,Costos!$D:$D,"<"&EDATE(A6,1)) -> 1397966.6 | E6: =SUMIFS(Costos!$N:$N,Costos!$D:$D,">="&A6,Costos!$D:$D,"<"&EDATE(A6,1)) -> 21764207 | F6: =IFERROR(E6/$E$16,0) -> 0.056673923 | H6: JSA DISTRIBUCIONES S.A.S. | I6: 901649254 | J6: =COUNTIFS(Costos!$E:$E,I6) -> 10 | K6: =SUMIFS(Costos!$N:$N,Costos!$E:$E,I6) -> 62141981 | L6: =IFERROR(K6/$E$16,0) -> 0.16181751
A7: =EDATE(A6,1) -> 45748 | B7: =COUNTIFS(Costos!$D:$D,">="&A7,Costos!$D:$D,"<"&EDATE(A7,1)) -> 47 | C7: =SUMIFS(Costos!$I:$I,Costos!$D:$D,">="&A7,Costos!$D:$D,"<"&EDATE(A7,1)) -> 55238334 | D7: =SUMIFS(Costos!$J:$J,Costos!$D:$D,">="&A7,Costos!$D:$D,"<"&EDATE(A7,1)) -> 1783437.4 | E7: =SUMIFS(Costos!$N:$N,Costos!$D:$D,">="&A7,Costos!$D:$D,"<"&EDATE(A7,1)) -> 57100357 | F7: =IFERROR(E7/$E$16,0) -> 0.14868914 | H7: GRUPO LEDACOM SAS | I7: 901476410 | J7: =COUNTIFS(Costos!$E:$E,I7) -> 43 | K7: =SUMIFS(Costos!$N:$N,Costos!$E:$E,I7) -> 27995900 | L7: =IFERROR(K7/$E$16,0) -> 0.07290123
A8: =EDATE(A7,1) -> 45778 | B8: =COUNTIFS(Costos!$D:$D,">="&A8,Costos!$D:$D,"<"&EDATE(A8,1)) -> 38 | C8: =SUMIFS(Costos!$I:$I,Costos!$D:$D,">="&A8,Costos!$D:$D,"<"&EDATE(A8,1)) -> 22788363 | D8: =SUMIFS(Costos!$J:$J,Costos!$D:$D,">="&A8,Costos!$D:$D,"<"&EDATE(A8,1)) -> 578569.4 | E8: =SUMIFS(Costos!$N:$N,Costos!$D:$D,">="&A8,Costos!$D:$D,"<"&EDATE(A8,1)) -> 23382555 | F8: =IFERROR(E8/$E$16,0) -> 0.060888095 | H8: SYSCOM COLOMBIA SAS | I8: 901192317 | J8: =COUNTIFS(Costos!$E:$E,I8) -> 22 | K8: =SUMIFS(Costos!$N:$N,Costos!$E:$E,I8) -> 27900207 | L8: =IFERROR(K8/$E$16,0) -> 0.072652046
A9: =EDATE(A8,1) -> 45809 | B9: =COUNTIFS(Costos!$D:$D,">="&A9,Costos!$D:$D,"<"&EDATE(A9,1)) -> 36 | C9: =SUMIFS(Costos!$I:$I,Costos!$D:$D,">="&A9,Costos!$D:$D,"<"&EDATE(A9,1)) -> 18882528 | D9: =SUMIFS(Costos!$J:$J,Costos!$D:$D,">="&A9,Costos!$D:$D,"<"&EDATE(A9,1)) -> 204863.51 | E9: =SUMIFS(Costos!$N:$N,Costos!$D:$D,">="&A9,Costos!$D:$D,"<"&EDATE(A9,1)) -> 19090198 | F9: =IFERROR(E9/$E$16,0) -> 0.049710811 | H9: KASKEY COLOMBIA SAS | I9: 901334425 | J9: =COUNTIFS(Costos!$E:$E,I9) -> 2 | K9: =SUMIFS(Costos!$N:$N,Costos!$E:$E,I9) -> 14327985 | L9: =IFERROR(K9/$E$16,0) -> 0.037310024
A10: =EDATE(A9,1) -> 45839 | B10: =COUNTIFS(Costos!$D:$D,">="&A10,Costos!$D:$D,"<"&EDATE(A10,1)) -> 62 | C10: =SUMIFS(Costos!$I:$I,Costos!$D:$D,">="&A10,Costos!$D:$D,"<"&EDATE(A10,1)) -> 29734616 | D10: =SUMIFS(Costos!$J:$J,Costos!$D:$D,">="&A10,Costos!$D:$D,"<"&EDATE(A10,1)) -> 1786912.5 | E10: =SUMIFS(Costos!$N:$N,Costos!$D:$D,">="&A10,Costos!$D:$D,"<"&EDATE(A10,1)) -> 31541540 | F10: =IFERROR(E10/$E$16,0) -> 0.082134063 | H10: GLOBAL-TEC S.A.S | I10: 900762275 | J10: =COUNTIFS(Costos!$E:$E,I10) -> 14 | K10: =SUMIFS(Costos!$N:$N,Costos!$E:$E,I10) -> 8247465.9 | L10: =IFERROR(K10/$E$16,0) -> 0.021476374
A11: =EDATE(A10,1) -> 45870 | B11: =COUNTIFS(Costos!$D:$D,">="&A11,Costos!$D:$D,"<"&EDATE(A11,1)) -> 56 | C11: =SUMIFS(Costos!$I:$I,Costos!$D:$D,">="&A11,Costos!$D:$D,"<"&EDATE(A11,1)) -> 32656329 | D11: =SUMIFS(Costos!$J:$J,Costos!$D:$D,">="&A11,Costos!$D:$D,"<"&EDATE(A11,1)) -> 1124381.6 | E11: =SUMIFS(Costos!$N:$N,Costos!$D:$D,">="&A11,Costos!$D:$D,"<"&EDATE(A11,1)) -> 33790703 | F11: =IFERROR(E11/$E$16,0) -> 0.087990878 | H11: TYU IMPORTACIONES S.A. | I11: 900181068 | J11: =COUNTIFS(Costos!$E:$E,I11) -> 6 | K11: =SUMIFS(Costos!$N:$N,Costos!$E:$E,I11) -> 8071062.9 | L11: =IFERROR(K11/$E$16,0) -> 0.021017021
A12: =EDATE(A11,1) -> 45901 | B12: =COUNTIFS(Costos!$D:$D,">="&A12,Costos!$D:$D,"<"&EDATE(A12,1)) -> 66 | C12: =SUMIFS(Costos!$I:$I,Costos!$D:$D,">="&A12,Costos!$D:$D,"<"&EDATE(A12,1)) -> 33979493 | D12: =SUMIFS(Costos!$J:$J,Costos!$D:$D,">="&A12,Costos!$D:$D,"<"&EDATE(A12,1)) -> 3270844.7 | E12: =SUMIFS(Costos!$N:$N,Costos!$D:$D,">="&A12,Costos!$D:$D,"<"&EDATE(A12,1)) -> 37258737 | F12: =IFERROR(E12/$E$16,0) -> 0.097021626 | H12: STEFANO ZINNO | I12: 700108357 | J12: =COUNTIFS(Costos!$E:$E,I12) -> 38 | K12: =SUMIFS(Costos!$N:$N,Costos!$E:$E,I12) -> 7221500 | L12: =IFERROR(K12/$E$16,0) -> 0.018804762
A13: =EDATE(A12,1) -> 45931 | B13: =COUNTIFS(Costos!$D:$D,">="&A13,Costos!$D:$D,"<"&EDATE(A13,1)) -> 70 | C13: =SUMIFS(Costos!$I:$I,Costos!$D:$D,">="&A13,Costos!$D:$D,"<"&EDATE(A13,1)) -> 37808641 | D13: =SUMIFS(Costos!$J:$J,Costos!$D:$D,">="&A13,Costos!$D:$D,"<"&EDATE(A13,1)) -> 1276540 | E13: =SUMIFS(Costos!$N:$N,Costos!$D:$D,">="&A13,Costos!$D:$D,"<"&EDATE(A13,1)) -> 39089143 | F13: =IFERROR(E13/$E$16,0) -> 0.101788 | H13: KLEYMAN YONATHAN VERGARA GONZALEZ | I13: 93397337 | J13: =COUNTIFS(Costos!$E:$E,I13) -> 31 | K13: =SUMIFS(Costos!$N:$N,Costos!$E:$E,I13) -> 6510000 | L13: =IFERROR(K13/$E$16,0) -> 0.016952018
A14: =EDATE(A13,1) -> 45962 | B14: =COUNTIFS(Costos!$D:$D,">="&A14,Costos!$D:$D,"<"&EDATE(A14,1)) -> 64 | C14: =SUMIFS(Costos!$I:$I,Costos!$D:$D,">="&A14,Costos!$D:$D,"<"&EDATE(A14,1)) -> 24941632 | D14: =SUMIFS(Costos!$J:$J,Costos!$D:$D,">="&A14,Costos!$D:$D,"<"&EDATE(A14,1)) -> 2392934.6 | E14: =SUMIFS(Costos!$N:$N,Costos!$D:$D,">="&A14,Costos!$D:$D,"<"&EDATE(A14,1)) -> 27344365 | F14: =IFERROR(E14/$E$16,0) -> 0.071204635 | H14: FCE COLOMBIA S A S | I14: 901718849 | J14: =COUNTIFS(Costos!$E:$E,I14) -> 4 | K14: =SUMIFS(Costos!$N:$N,Costos!$E:$E,I14) -> 5064232 | L14: =IFERROR(K14/$E$16,0) -> 0.013187243
A15: =EDATE(A14,1) -> 45992 | B15: =COUNTIFS(Costos!$D:$D,">="&A15,Costos!$D:$D,"<"&EDATE(A15,1)) -> 72 | C15: =SUMIFS(Costos!$I:$I,Costos!$D:$D,">="&A15,Costos!$D:$D,"<"&EDATE(A15,1)) -> 69061226 | D15: =SUMIFS(Costos!$J:$J,Costos!$D:$D,">="&A15,Costos!$D:$D,"<"&EDATE(A15,1)) -> 10952720 | E15: =SUMIFS(Costos!$N:$N,Costos!$D:$D,">="&A15,Costos!$D:$D,"<"&EDATE(A15,1)) -> 80016983 | F15: =IFERROR(E15/$E$16,0) -> 0.20836396 | H15: Otros (65 prov.) | J15: =B16-SUM(J5:J14) -> 222 | K15: =E16-SUM(K5:K14) -> 50285257 | L15: =IFERROR(K15/$E$16,0) -> 0.13094264
A16: TOTAL | B16: =SUM(B5:B15) -> 554 | C16: =SUM(C5:C15) -> 3.5910369e+08 | D16: =SUM(D5:D15) -> 24769170 | E16: =SUM(E5:E15) -> 3.8402507e+08 | F16: =IFERROR(E16/$E$16,0) -> 1 | H16: TOTAL | J16: =SUM(J5:J15) -> 554 | K16: =SUM(K5:K15) -> 3.8402507e+08 | L16: =IFERROR(K16/$E$16,0) -> 1
H19: Indicadores clave
H20: Costo total (COP) | I20: =E16 -> 3.8402507e+08
H21: Total facturas | I21: =B16 -> 554
H22: Promedio mensual | I22: =AVERAGE(E5:E15) -> 34911370
H23: Factura promedio | I23: =E16/B16 -> 693186.05
H24: Mes de mayor costo | I24: =INDEX(A5:A15,MATCH(MAX(E5:E15),E5:E15,0)) -> 45992
H25: Mayor proveedor | I25: =H5&" ("&TEXT(L5,"0.0%")&")" -> IMPRESISTEM S A S (43.3%)

Sheet Hoja1
A1: NIT Emisor | B1: Nombre Emisor | C1: Suma de SUBTOTAL | D1: Suma de IVA | E1: Suma de IC | F1: Suma de INC | G1: Suma de INC Bolsas
A2: 3486666 | B2: RAMON ALCIDES CIFUENTES SERNA | C2: 3710000 | D2: 0 | E2: 0 | F2: 0 | G2: 0
A3: 8026157 | B3: ANDRES FELIPE VELEZ MUÑOZ | C3: 207000 | D3: 39330 | E3: 0 | F3: 0 | G3: 0
A4: 32257553 | B4: ROLDAN OLGA AMPARO | C4: 1500000 | D4: 0 | E4: 0 | F4: 0 | G4: 0
A5: 43645742 | B5: ARBELAEZ GIRALDO GLORIA CRISTINA | C5: 531092.38 | D5: 100907.55 | E5: 0 | F5: 0 | G5: 0
A6: 70561688 | B6: DIEGO ALONSO MURILLO GUZMAN | C6: 16000 | D6: 3040 | E6: 0 | F6: 0 | G6: 0
A7: 70780282 | B7: JOSE ANGEL LOPEZ VILLA | C7: 16000 | D7: 0 | E7: 0 | F7: 0 | G7: 0
A8: 70978458 | B8: PEREZ PEREZ JAIDER ESNEIDER | C8: 29411.76 | D8: 5588.23 | E8: 0 | F8: 0 | G8: 0
A9: 71388800 | B9: ARISTIZABAL SERNA DANIEL ALEJANDRO | C9: 8403 | D9: 1597 | E9: 0 | F9: 0 | G9: 0
A10: 91076199 | B10: VARGAS MIRANDA LUIS FERNANDO | C10: 429411.77 | D10: 81588.23 | E10: 0 | F10: 0 | G10: 0
A11: 93397337 | B11: KLEYMAN YONATHAN VERGARA GONZALEZ | C11: 6510000 | D11: 0 | E11: 0 | F11: 0 | G11: 0
A12: 700108357 | B12: STEFANO ZINNO | C12: 7221500 | D12: 0 | E12: 0 | F12: 0 | G12: 0
A13: 800091549 | B13: IMPRESISTEM S A S | C13: 166193551 | D13: 65930 | E13: 0 | F13: 0 | G13: 0
... A65: 901575358 | B65: CLOVER COMPANY S.A.S | C65: 3783024.1 | D65: 718774.58 | E65: 0 | F65: 0 | G65: 0
A66: 901606621 | B66: LA VELERIA PARAFIN S.A.S. | C66: 163697.4 | D66: 31102.51 | E66: 0 | F66: 0 | G66: 0 | I66: PAGADO | J66: SUB | K66: RT | L66: 2205
A67: 901649254 | B67: JSA DISTRIBUCIONES S.A.S. | C67: 52220152 | D67: 9921828.9 | E67: 0 | F67: 0 | G67: 0 | I67: 3130000 | J67: =+GETPIVOTDATA("Suma de SUBTOTAL",$A$1,"NIT Emisor",901649254,"Nombre Emisor","JSA DISTRIBUCIONES S.A.S.")+GETPIVOTDATA("Suma de IVA",$A$1,"NIT Emisor",901649254,"Nombre Emisor","JSA DISTRIBUCIONES S.A.S.") -> 62141981 | K67: =+GETPIVOTDATA("Suma de SUBTOTAL",$A$1,"NIT Emisor",901649254,"Nombre Emisor","JSA DISTRIBUCIONES S.A.S.")*2.5% -> 1305503.8 | L67: =+J67-I67-K67 -> 57706477
A68: 901660770 | B68: CRISPINO S.A.S. | C68: 185881.47 | D68: 0 | E68: 0 | F68: 13518.51 | G68: 0
A69: 901718849 | B69: FCE COLOMBIA S A S | C69: 5064232 | D69: 0 | E69: 0 | F69: 0 | G69: 0
A70: 901784030 | B70: BOMBA FOODS SAS | C70: 161759.25 | D70: 0 | E70: 0 | F70: 12940.75 | G70: 0
A71: 901939945 | B71: JOTTAFOODS SAS | C71: 197075.65 | D71: 35924.37 | E71: 0 | F71: 0 | G71: 0
A72: 901972453 | B72: TECNOVÍA SAS | C72: 92782 | D72: 17628.58 | E72: 0 | F72: 0 | G72: 0
A73: 1003880015 | B73: PAEZ BALLESTEROS CESAR NICOLAS | C73: 202000 | D73: 0 | E73: 0 | F73: 0 | G73: 0
A74: 1128277256 | B74: ARISTIZABAL GOMEZ JUAN DAVID | C74: 518487.4 | D74: 98512.61 | E74: 0 | F74: 0 | G74: 0
A75: 1128404762 | B75: Bodega Digital Medellin | C75: 60000 | D75: 11400 | E75: 0 | F75: 0 | G75: 0
A76: Total general | C76: 3.5878269e+08 | D76: 24769170 | E76: 5844 | F76: 146053.18 | G76: 318
C79: =+GETPIVOTDATA("Suma de SUBTOTAL",$A$1)+GETPIVOTDATA("Suma de IC",$A$1)+GETPIVOTDATA("Suma de INC",$A$1)+GETPIVOTDATA("Suma de INC Bolsas",$A$1) -> 3.589349e+08 | D79: Costos
C80: =+GETPIVOTDATA("Suma de SUBTOTAL",$A$1)-C79 -> -152215.18 | G80: =+GETPIVOTDATA("Suma de INC Bolsas",$A$1)+GETPIVOTDATA("Suma de INC",$A$1)+GETPIVOTDATA("Suma de IC",$A$1) -> 152215.18 | H80: ok
